{"lands":{"autotiles":[],"floors":[{"k":[20,0,0,20,0],"v":{"t":[3,0]}},{"k":[20,0,0,19,0],"v":{"t":[3,0]}},{"k":[19,0,0,20,0],"v":{"t":[3,0]}},{"k":[20,0,0,18,0],"v":{"t":[3,0]}},{"k":[19,0,0,19,0],"v":{"t":[3,0]}},{"k":[18,0,0,20,0],"v":{"t":[3,0]}},{"k":[20,0,0,17,0],"v":{"t":[3,0]}},{"k":[19,0,0,18,0],"v":{"t":[3,0]}},{"k":[18,0,0,19,0],"v":{"t":[3,0]}},{"k":[17,0,0,20,0],"v":{"t":[3,0]}},{"k":[16,0,0,16,0],"v":{"t":[3,0]}},{"k":[20,0,0,16,0],"v":{"t":[3,0]}},{"k":[19,0,0,17,0],"v":{"t":[3,0]}},{"k":[18,0,0,18,0],"v":{"t":[3,0]}},{"k":[17,0,0,19,0],"v":{"t":[3,0]}},{"k":[16,0,0,20,0],"v":{"t":[3,0]}},{"k":[19,0,0,16,0],"v":{"t":[3,0]}},{"k":[18,0,0,17,0],"v":{"t":[3,0]}},{"k":[17,0,0,18,0],"v":{"t":[3,0]}},{"k":[16,0,0,19,0],"v":{"t":[3,0]}},{"k":[18,0,0,16,0],"v":{"t":[3,0]}},{"k":[17,0,0,17,0],"v":{"t":[3,0]}},{"k":[16,0,0,18,0],"v":{"t":[3,0]}},{"k":[17,0,0,16,0],"v":{"t":[3,0]}},{"k":[16,0,0,17,0],"v":{"t":[3,0]}}]},"moun":{"a":[],"o":[]},"objs":{"list":[]},"objs3d":{"a":[],"o":[]},"sprites":{"list":[{"k":[16,0,0,17,0],"v":{"f":false,"k":7,"t":[2,9,4,5]}},{"k":[18,0,0,20,0],"v":{"f":false,"k":7,"t":[2,9,4,5]}},{"k":[18,0,0,19,0],"v":{"f":false,"k":7,"t":[2,9,4,5]}},{"k":[17,0,0,20,0],"v":{"f":false,"k":7,"t":[2,9,4,5]}},{"k":[20,0,0,17,0],"v":{"f":false,"k":7,"t":[2,9,4,5]}},{"k":[17,0,0,19,0],"v":{"f":false,"k":7,"t":[2,9,4,5]}},{"k":[20,0,0,16,0],"v":{"f":false,"k":7,"t":[2,9,4,5]}},{"k":[17,0,0,18,0],"v":{"f":false,"k":7,"t":[2,9,4,5]}},{"k":[16,0,0,19,0],"v":{"f":false,"k":7,"t":[2,9,4,5]}},{"k":[16,0,0,18,0],"v":{"f":false,"k":7,"t":[2,9,4,5]}}],"overflow":[],"walls":[]}}